botbuilder/ai/__init__.py
botbuilder/ai/about.py
botbuilder/ai/luis/__init__.py
botbuilder/ai/luis/activity_util.py
botbuilder/ai/luis/luis_application.py
botbuilder/ai/luis/luis_prediction_options.py
botbuilder/ai/luis/luis_recognizer.py
botbuilder/ai/luis/luis_recognizer_internal.py
botbuilder/ai/luis/luis_recognizer_options.py
botbuilder/ai/luis/luis_recognizer_options_v2.py
botbuilder/ai/luis/luis_recognizer_options_v3.py
botbuilder/ai/luis/luis_recognizer_v2.py
botbuilder/ai/luis/luis_recognizer_v3.py
botbuilder/ai/luis/luis_telemetry_constants.py
botbuilder/ai/luis/luis_util.py
botbuilder/ai/qna/__init__.py
botbuilder/ai/qna/qna_dialog_response_options.py
botbuilder/ai/qna/qnamaker.py
botbuilder/ai/qna/qnamaker_endpoint.py
botbuilder/ai/qna/qnamaker_options.py
botbuilder/ai/qna/qnamaker_telemetry_client.py
botbuilder/ai/qna/dialogs/__init__.py
botbuilder/ai/qna/dialogs/qnamaker_dialog.py
botbuilder/ai/qna/dialogs/qnamaker_dialog_options.py
botbuilder/ai/qna/models/__init__.py
botbuilder/ai/qna/models/feedback_record.py
botbuilder/ai/qna/models/feedback_records.py
botbuilder/ai/qna/models/generate_answer_request_body.py
botbuilder/ai/qna/models/join_operator.py
botbuilder/ai/qna/models/metadata.py
botbuilder/ai/qna/models/prompt.py
botbuilder/ai/qna/models/qna_request_context.py
botbuilder/ai/qna/models/qna_response_context.py
botbuilder/ai/qna/models/qnamaker_trace_info.py
botbuilder/ai/qna/models/query_result.py
botbuilder/ai/qna/models/query_results.py
botbuilder/ai/qna/models/ranker_types.py
botbuilder/ai/qna/models/train_request_body.py
botbuilder/ai/qna/utils/__init__.py
botbuilder/ai/qna/utils/active_learning_utils.py
botbuilder/ai/qna/utils/generate_answer_utils.py
botbuilder/ai/qna/utils/http_request_utils.py
botbuilder/ai/qna/utils/qna_card_builder.py
botbuilder/ai/qna/utils/qna_telemetry_constants.py
botbuilder/ai/qna/utils/train_utils.py
botbuilder_ai-4.17.1.dist-info/METADATA
botbuilder_ai-4.17.1.dist-info/WHEEL
botbuilder_ai-4.17.1.dist-info/top_level.txt
botbuilder_ai-4.17.1.dist-info/RECORD
