Metadata-Version: 2.1
Name: botbuilder-ai
Version: 4.17.1
Summary: Microsoft Bot Framework Bot Builder
Home-page: https://www.github.com/Microsoft/botbuilder-python
Author: Microsoft
License: MIT
Keywords: botbuilder-ai LUIS QnAMaker bots ai botframework botbuilder
Classifier: Programming Language :: Python :: 3.7
Classifier: Intended Audience :: Developers
Classifier: License :: OSI Approved :: MIT License
Classifier: Operating System :: OS Independent
Classifier: Development Status :: 5 - Production/Stable
Classifier: Topic :: Scientific/Engineering :: Artificial Intelligence
Requires-Dist: azure-cognitiveservices-language-luis==0.2.0
Requires-Dist: botbuilder-schema==4.17.1
Requires-Dist: botbuilder-core==4.17.1
Requires-Dist: aiohttp<4.0,>=3.10
Requires-Dist: aiounittest>=1.1.0
